icshelper/Calendar.py
icshelper/Event.py
icshelper/Util.py
icshelper/__init__.py
icshelper-0.0.1.dist-info/LICENSE
icshelper-0.0.1.dist-info/METADATA
icshelper-0.0.1.dist-info/WHEEL
icshelper-0.0.1.dist-info/top_level.txt
icshelper-0.0.1.dist-info/RECORD
